refreshcss/__init__.py
refreshcss/cli.py
refreshcss/css/__init__.py
refreshcss/css/parser.py
refreshcss/filters.py
refreshcss/html/__init__.py
refreshcss/html/file.py
refreshcss/html/site.py
refreshcss/main.py
refreshcss/utils/__init__.py
refreshcss/utils/path.py
refreshcss-0.6.0.dist-info/WHEEL
refreshcss-0.6.0.dist-info/entry_points.txt
refreshcss-0.6.0.dist-info/METADATA
refreshcss-0.6.0.dist-info/RECORD
