Metadata-Version: 2.3
Name: refreshcss
Version: 0.6.0
Summary: Removes unused classes, ids, and element selectors from CSS.
Keywords: django,python,css,html
Author: adamghill
Author-email: adamghill <adamghill@yahoo.com>
License: MIT
Classifier: Development Status :: 4 - Beta
Classifier: Intended Audience :: Developers
Classifier: License :: OSI Approved :: MIT License
Classifier: Programming Language :: Python :: 3
Classifier: Programming Language :: Python :: 3.10
Classifier: Programming Language :: Python :: 3.11
Classifier: Programming Language :: Python :: 3.12
Classifier: Programming Language :: Python :: 3.13
Requires-Dist: justhtml>=0.32.0
Requires-Dist: tinycss2>=1.5.1
Requires-Dist: click>=8.1.7 ; extra == 'cli'
Requires-Dist: charset-normalizer>=3.3.2 ; extra == 'cli'
Requires-Python: >=3.10
Project-URL: Documentation, https://github.com/adamghill/refreshcss/
Project-URL: Funding, https://github.com/sponsors/adamghill
Project-URL: Homepage, https://github.com/adamghill/refreshcss/
Project-URL: Repository, https://github.com/adamghill/refreshcss/
Provides-Extra: cli
